README.md
setup.py
hyjhub/__init__.py
hyjhub/_core.py
hyjhub.egg-info/PKG-INFO
hyjhub.egg-info/SOURCES.txt
hyjhub.egg-info/dependency_links.txt
hyjhub.egg-info/top_level.txt