Metadata-Version: 2.1
Name: hyjhub
Version: 0.0.0
Summary: a demo coehun
Home-page: https://github.com/thgpddl
Author: thgpddl
Author-email: thgpddl@163.com
License: Apache 2.0
Keywords: hub
Platform: UNKNOWN
Classifier: Development Status :: 3 - Alpha
Classifier: Intended Audience :: Developers
Classifier: Programming Language :: Python :: 3
Classifier: Programming Language :: Python :: 3.7
Classifier: Programming Language :: Python :: 3.8
Classifier: Programming Language :: Python :: 3.9
Classifier: Programming Language :: Python :: 3.10
Classifier: Programming Language :: Python :: 3 :: Only
Classifier: License :: OSI Approved :: MIT License
Classifier: Operating System :: OS Independent
